fs2elastic/__init__.py
fs2elastic/confbuilder.py
fs2elastic/dataset_processor.py
fs2elastic/es_handler.py
fs2elastic/fs2elastic.py
fs2elastic/typings.py
fs2elastic-0.1.2.dist-info/LICENSE
fs2elastic-0.1.2.dist-info/METADATA
fs2elastic-0.1.2.dist-info/WHEEL
fs2elastic-0.1.2.dist-info/entry_points.txt
fs2elastic-0.1.2.dist-info/top_level.txt
fs2elastic-0.1.2.dist-info/RECORD
