Metadata-Version: 2.1
Name: fs2elastic
Version: 0.1.2
Summary: Python based CLI for Syncing File System based Data (CSV file etc.) to Elasticsearch.
Author-email: Pankaj Jackson <pankajackson@live.co.uk>
License: MIT License
Project-URL: Homepage, https://github.com/pankajackson/FS2Elastic
Project-URL: Bug Tracker, https://github.com/pankajackson/FS2Elastic/issues
Project-URL: Source, https://github.com/pankajackson/FS2Elastic
Keywords: csv,sync,elasticsearch,data
Classifier: Programming Language :: Python :: 3
Classifier: Development Status :: 4 - Beta
Classifier: Intended Audience :: Science/Research
Classifier: License :: OSI Approved :: GNU General Public License v3 or later (GPLv3+)
Classifier: Operating System :: Unix
Requires-Python: >=3.10
License-File: LICENSE
Requires-Dist: elasticsearch
Requires-Dist: openpyxl
Requires-Dist: pandas
Requires-Dist: pydantic
Requires-Dist: retry
Requires-Dist: toml
Requires-Dist: watchdog
Requires-Dist: xlrd
